toolini/__init__.py
toolini/main.py
toolini-0.0.1.dist-info/METADATA
toolini-0.0.1.dist-info/WHEEL
toolini-0.0.1.dist-info/top_level.txt
toolini-0.0.1.dist-info/RECORD
